{
  "project_info": {
    "project_number": "518041808056",
    "project_id": "library-app-4cf09",
    "storage_bucket": "library-app-4cf09.appspot.com"
  },
  "client": [
    {
      "client_info": {
        "mobilesdk_app_id": "1:518041808056:android:bcaa81440ce0152ec7984d",
        "android_client_info": {
          "package_name": "com.example.libraryapp"
        }
      },
      "oauth_client": [
        {
          "client_id": "518041808056-o0oqnf41bn9b77v7jqlkf21b1c5b24k1.apps.googleusercontent.com",
          "client_type": 1,
          "android_info": {
            "package_name": "com.example.libraryapp",
            "certificate_hash": "eb02e1ef7cb7277ff0aaa488a1f09229c52adc11"
          }
        },
        {
          "client_id": "518041808056-ga21v4eaqbve1dfuhseolum604vjv7vh.apps.googleusercontent.com",
          "client_type": 3
        }
      ],
      "api_key": [
        {
          "current_key": "AIzaSyAF21CdTN_CvYNR8yQEg2-Av-9HwBlhgok"
        }
      ],
      "services": {
        "appinvite_service": {
          "other_platform_oauth_client": [
            {
              "client_id": "518041808056-ga21v4eaqbve1dfuhseolum604vjv7vh.apps.googleusercontent.com",
              "client_type": 3
            }
          ]
        }
      }
    }
  ],
  "configuration_version": "1"
}